TDMYSA/__init__.py
TDMYSA-0.2.dist-info/METADATA
TDMYSA-0.2.dist-info/WHEEL
TDMYSA-0.2.dist-info/top_level.txt
TDMYSA-0.2.dist-info/RECORD
